Workbook

Sheet Test Cases
A1: Test Case ID | B1: Group | C1: Type | D1: Reported issue | E1: Test Scenario | F1: Where to run it (exact screen) | G1: Where to verify the result | H1: Preconditions | I1: Test Steps | J1: Expected Result | K1: Actual Result | L1: Pass / Fail | M1: Tested By | N1: Date | O1: Notes / Defect ref
A2: ER-01 | B2: A. Executive Readiness - saving | C2: Positive | D2: ER: dropdowns and Add do not upload | E2: A 1-5 score is stored the moment it is pressed | F2: Executive Readiness > Readiness tab > Phase 1 > Step 1.1 Assessment Battery > section B "AI Fluency". Control: the 1-5 buttons on "Foundational understanding *". URL: /apps/enterprises/executive-readiness/step/1.1 | G2: Ben's window: same step, section B - the number appears with NO reload. After reload: still set for both. DB: workspaces (module 'exec-readiness') > doc $.assessments.fluency.foundational; rev goes up by 1. Network: one POST /workspace/patch naming "assessments". | H2: Ann and Ben are both signed in to the same organization with Executive Readiness open. Ben is on the same assessment page as Ann. | I2: 1. Ann presses a 1-5 score on a readiness question. 2. Ann does NOT navigate anywhere and does not click anything else. 3. Ben waits 10 seconds and looks at the same question. 4. Ann reloads her own page. | J2: Ben sees the score within about 10 seconds without reloading, and it is still there after Ann reloads. Pressing a score is a save on its own - it must not need a page change to be stored.
A3: ER-02 | B3: A. Executive Readiness - saving | C3: Defect | D3: ER: dropdowns and Add do not upload | E3: A dropdown choice is stored without navigating away | F3: Executive Readiness > Step 1.1 > section D "Leadership Structure Baseline". Control: dropdown "Who currently owns AI transformation? *" [ad_ownership]. Second dropdown, if needed: Step 2.1 Leadership Structure Lab > "Board AI oversight structure" [st_boardStructure]. URL: /apps/enterprises/executive-readiness/step/1.1 (and /step/2.1) | G3: Ben's window: section D after his reload. Ann: F5 without leaving the page first. DB: doc $.assessments.structure.ownership (module 'exec-readiness'). The defect is reproduced if the value only reaches the DB after Ann changes page - watch for a POST that fires on navigation instead of on change. | H3: Ann on an Executive Readiness page that has at least one dropdown (select) field. Ben signed in on the same program in a second browser. | I3: 1. Ann chooses a value in a dropdown. 2. Ann stays exactly where she is for 15 seconds - no page change, no other click. 3. Ben reloads and checks that field. 4. Ann reloads and checks it too. | J3: The chosen value is stored and visible to Ben, and survives Ann's reload. This was reported as NOT saving - a dropdown was only ever written when the user happened to leave the page, so choosing one and closing the tab lost it.
A4: ER-03 | B4: A. Executive Readiness - saving | C4: Positive | D4: ER: dropdowns and Add do not upload | E4: A row added with "Add" is stored without navigating away | F4: Executive Readiness > Step 3.3 Middle Management > the workflow form (Workflow / AI role / Human role) > "+ Add Workflow". Same shape elsewhere: Step 3.4 Values Architecture "+ Add Principle" [ov_principle / ov_domain]; Step 1.4 "+ Add to Scan" [dep_skill / dep_tool]; Step 2.1 "+ Add to org chart". Remember: an ER "Add" reads the little form ABOVE the button and appends the finished row - there is no empty row to type into afterwards. URL: /apps/enterprises/executive-readiness/step/3.3 | G4: Ben's window: the new row, with Ann's text in it, after his reload (allow ~4 s for the save in flight). Ann: row still there after F5, with no page change in between. DB: doc $.mmActivation.workflows (module 'exec-readiness') - JSON_LENGTH grows by 1; $.orgValues / $.depScan for the alternatives. Network: the Add itself produces a POST; nothing may wait for a navigation. | H4: Ann on an Executive Readiness step that builds a list - Phase 3.3 (workflows, human-only decisions), Phase 3.4 (principles) or the org chart on 2.1. NOTE: this program fills the fields FIRST and then presses Add; there is no empty row to type into afterwards. | I4: 1. Ann fills in every field of the little "Add" form (the text boxes and any dropdown above the button). 2. Ann presses "+ Add" - the row appears in the list. 3. Ann waits 15 seconds without leaving the page and without clicking anything else. 4. Ben reloads and counts the rows. 5. Ann reloads and counts them again. | J4: The new row, with everything Ann typed in it, exists for both of them after reload. An "Add" is a real change and must be uploaded like a score - it must not wait for a page change. Allow up to about 4 seconds for it to arrive; a save that has only just been made is still on its way.
A5: ER-04 | B5: A. Executive Readiness - saving | C5: Defect | D5: AIP: sub-fields only save on blur | E5: Text typed into a field is stored while it is being typed | F5: Executive Readiness, any long-text answer. Primary: Step 1.1 section A > "Mission statement *" [ap_mission]. Type a full sentence and LEAVE THE CURSOR IN IT. Also worth running on a box that only exists after an Add: Step 1.2 Leadership Landscape > "+ Add Leader" > "Change leadership experience" [ldr_changeExp]. URL: /apps/enterprises/executive-readiness/step/1.1 (and /apps/enterprises/executive-readiness/step/1.2) | G5: Ben's window: the text after his reload, about a second after Ann stops typing. Ann: F5 with the caret still in the box - no click away, no button, no page change first. DB: doc $.assessments.purpose.mission (module 'exec-readiness'); $.leaders[*].changeExp for the leader-card variant. These boxes used to be banked only on blur or navigation - if the text needs a click elsewhere to survive, the case fails. | H5: Ann on an Executive Readiness step with written answers (for example 1.1 section D, or any phase step with long text boxes). | I5: 1. Ann types a full sentence into an answer and LEAVES THE CURSOR IN IT. 2. Ann waits 10 seconds without clicking away and without leaving the page. 3. Ben reloads and reads the same answer. 4. Ann presses F5 without clicking away first. | J5: The sentence reaches the database about a second after Ann stops typing - Ben sees it, and it is still there after Ann's reload. Nothing may depend on her clicking out of the box, pressing a button, or moving to another page first.
A6: ER-05 | B6: A. Executive Readiness - saving | C6: Positive | D6: Both: whole module uploaded | E6: A long written answer on a page reaches the database | F6: Executive Readiness > Step 1.1 > section A "Strategic Clarity & Purpose Alignment". Controls: "Mission statement *" [ap_mission] and "Top 3 strategic goals *", then move on with the section buttons and the sidebar to Step 1.2. URL: /apps/enterprises/executive-readiness/step/1.1 | G6: Ann: back on section A after the round trip. Ben's window: same section after his reload. DB: doc $.assessments.purpose.mission (module 'exec-readiness'); step_answers rows for step_id '1.1'. | H6: Ann on an Executive Readiness step with large text answers. | I6: 1. Ann writes several sentences into a text answer. 2. Ann moves to the next step using the normal navigation. 3. Ann comes back to the step. 4. Ben reloads his browser and opens the same step. | J6: The answer is there for Ann when she returns and for Ben after his reload. Nothing typed on the page is left behind by the move.
A7: ER-06 | B7: A. Executive Readiness - saving | C7: Defect | D7: Both: pulls and overwrites every 5s | E7: A half-typed answer survives another member's save | F7: Ann: Executive Readiness > Step 1.1 section A > "Mission statement *" [ap_mission], caret left in the box. Ben: anywhere else in the same program - Step 1.3 Risk Mapping 1-5 score, or Step 2.1 "Board AI oversight structure" - then clicks away so it saves. URL: /apps/enterprises/executive-readiness/step/1.1 and /apps/enterprises/executive-readiness/step/1.3 | G7: Ann's screen: her sentence and her caret unchanged across at least two 5-second polls (watch GET /workspace/rev tick in the Network tab). After reload: her text still there, and Ben's change present in its own section. DB: doc holds both $.assessments.purpose.mission and Ben's field. | H7: Ann and Ben both have Executive Readiness open. Ann is on a step with text answers. | I7: 1. Ann types a long sentence into an answer and leaves the cursor in it. She does not click away. 2. Within a second or two, Ben changes any value anywhere in the module and clicks away so it saves. 3. Ann keeps watching her screen for 20 seconds without touching anything. 4. Ann reloads. | J7: Ann's sentence stays exactly as she typed it and her cursor stays where it was - it is not cleared, shortened or reset to the stored value. After the reload it is still there. Ben's change appears elsewhere on the page.
A8: ER-07 | B8: A. Executive Readiness - saving | C8: Defect | D8: ER: uploads on every page move | E8: Moving between pages without typing uploads nothing | F8: Executive Readiness, five screens with NO typing: Home > Learn > Readiness overview > Phase 2 landing > Step 2.2 AI Collaboration Lab. Dev tools > Network, filter "workspace", list cleared first. URLs: /apps/enterprises/executive-readiness , /apps/enterprises/executive-readiness/learn , /apps/enterprises/executive-readiness/pipeline , /apps/enterprises/executive-readiness/phase/2 , /apps/enterprises/executive-readiness/step/2.2 | G8: Network: zero POST /workspace and zero POST /workspace/patch. Only GET /workspace/rev, once every 5 seconds. DB: workspaces.rev and updated_at for module 'exec-readiness' identical before and after the walk. | H8: Ann signed in to Executive Readiness. Browser dev tools open on the Network tab, filtered to "workspace". | I8: 1. Clear the network list. 2. Move through five different pages or steps without typing, clicking a score, or choosing anything. 3. Count the requests to /workspace and /workspace/patch. | J8: Zero uploads. It was reported that the module uploaded on every page move whether or not anything had changed - which is what let a person who was only reading overwrite somebody else's work.
A9: ER-08 | B9: A. Executive Readiness - saving | C9: Edge case | D9: ER: uploads on every page move | E9: An idle Executive Readiness window uploads nothing | F9: Executive Readiness > Step 1.1, window left untouched for 2 minutes, then ONE edit in section A. Dev tools > Network, filter "workspace". URL: /apps/enterprises/executive-readiness/step/1.1 | G9: Network: 0 POSTs in the idle window; exactly 1 POST after the single edit. DB: rev unchanged over the idle window, then +1 exactly. GET /workspace/rev repeating is expected and is not an upload. | H9: Ann signed in with the module open and the Network tab filtered to "workspace". | I9: 1. Leave the window untouched for 2 minutes. 2. Count uploads (POST), ignoring the /workspace/rev checks. 3. Make one edit and count again. | J9: Two minutes idle: zero uploads. One edit: exactly one upload. Only the small change-check (GET /workspace/rev) should repeat while nothing is happening.
A10: ER-09 | B10: A. Executive Readiness - saving | C10: Defect | D10: ER: uploads on every page move | E10: A page that was only read does not write its values back | F10: Both users on Executive Readiness > Step 1.1 section A, which already holds answers. Ann: reads only, then Step 1.1 > Step 1.2 > back. Ben: rewrites "Mission statement *" [ap_mission] and clicks away. URL: /apps/enterprises/executive-readiness/step/1.1 | G10: Both screens show Ben's rewritten text. DB: doc $.assessments.purpose.mission = Ben's value; workspaces.updated_by = Ben's users.public_id, NOT Ann's. Network on Ann's side: her navigation produces no POST at all. | H10: Ann and Ben both have the same Executive Readiness step open, and it already has answers on it. | I10: 1. Ann opens the step and READS it only - she types nothing and clicks nothing. 2. Ben rewrites one of the answers on that step and saves it. 3. Ann waits 10 seconds, then clicks to another page and back. 4. Both reload. | J10: Ben's rewritten answer stands on both screens. Ann's browser must not push the older text it was displaying back over Ben's change simply because she had the page open when he changed it.
A11: ER-10 | B11: A. Executive Readiness - saving | C11: Edge case | D11: ER: dropdowns and Add do not upload | E11: A score, a dropdown and an Add in quick succession | F11: No single Executive Readiness step carries a score, a dropdown and an Add together, so run two passes: Pass 1 - Step 4.3 First Leadership Review: press a 1-5 score and change its dropdown within ~3 seconds. Pass 2 - Step 1.4 Mindset Foundations: change "Importance"/"Risk" [dep_importance / dep_risk] and press "+ Add to Scan" within ~3 seconds. URLs: /apps/enterprises/executive-readiness/step/4.3 , /apps/enterprises/executive-readiness/step/1.4 | G11: Network: each pass sends 1-2 POSTs, not one per click. Ben's window: every value from both passes present after his reload. DB: doc holds the review score, the dropdown value and the new $.depScan row. | H11: Ann on a page that has all three controls. Network tab filtered to "workspace". | I11: 1. Within about 3 seconds: press a score, choose a dropdown value, and click "Add". 2. Wait 10 seconds and count the uploads. 3. Ben reloads and checks all three results. | J11: All three changes are stored and visible to Ben. They are sent together in one or two uploads rather than one per click - grouped, but never dropped.
A12: ER-11 | B12: A. Executive Readiness - saving | C12: Edge case | D12: ER: dropdowns and Add do not upload | E12: Reload immediately after a dropdown change | F12: Executive Readiness > Step 1.1 section D > dropdown "Who currently owns AI transformation? *" [ad_ownership], then F5 within half a second. URL: /apps/enterprises/executive-readiness/step/1.1 | G12: On screen after the reload: the NEW value, not the old stored one. Ben's window: same value after his reload. DB: doc $.assessments.structure.ownership. Network: the POST must be visible as leaving before or with the unload. | H12: Ann on an Executive Readiness page with a dropdown. | I12: 1. Ann changes a dropdown and presses F5 within half a second. 2. Check the field after the page has loaded. 3. Ben reloads and checks the same field. | J12: The new value is shown after the reload and Ben sees it too. The reload must not bring back the older stored value.
A13: ER-12 | B13: A. Executive Readiness - saving | C13: Negative | D13: Both: whole module uploaded | E13: Scores and dropdowns entered offline are sent on reconnect | F13: Executive Readiness > Step 1.1 with dev tools > Network > Offline ticked. Offline: two scores in section B, the section D dropdown, then Step 1.4 "+ Add to Scan". Back online, wait 15 s. URL: /apps/enterprises/executive-readiness/step/1.1 then /apps/enterprises/executive-readiness/step/1.4 | G13: On screen: an offline notice while disconnected. On reconnect: the queued POSTs appear in the Network tab and answer 200. Ben's window: all four changes after his reload. DB: doc holds $.assessments.fluency.*, $.assessments.structure.ownership and the new $.depScan row. | H13: Ann on an Executive Readiness page. Dev tools available to switch the network off. | I13: 1. Ann goes offline (dev tools > Network > Offline). 2. Ann presses two scores, changes a dropdown and adds a row. 3. Ann comes back online and waits 15 seconds. 4. Ben reloads. | J13: An offline notice is shown while disconnected. On reconnect all four changes are uploaded and Ben sees every one of them. Nothing entered offline is dropped.
... A59: SI-09 | B59: H. Sign-in and identity | C59: Positive | D59: Login: signed in as the org admin | E59: What the signed-in member can do matches who they are | F59: Two profiles side by side at /apps/enterprises/innovation-pipeline: Ben (ordinary member) and Ann (organization admin). Each opens More menu > Profile - the team list and organization details. | G59: Ben can read the team and edit only his own profile: no "+ Add team member", no delete, no organization editing. Ann has all three. API check: a POST /apps/api/users sent from Ben's session is refused by the server, not just hidden in the UI. | H59: Ben signed in as an ordinary member; Ann signed in as the organization admin, in a second browser. | I59: 1. On Ben's screen, open the team list and the organization details. 2. Try to add a member, delete a member and edit the organization. 3. Do the same as Ann. | J59: Ben can read the team and edit only his own profile; add, delete and organization editing are not offered to him. Ann has all of them. Rights follow the identity that was actually authenticated.

Sheet Test Environment
A1: Test environment — multi-user sync follow-up
A3: Everything in this suite runs against the local XAMPP install of the 90-Day Programs app. Read this sheet once, build the environment, then work down the Test Cases sheet: each case names the exact screen to run it on and the exact places to check the result.
A5: 1. The install under test
A7: Web root
A8: c:\xampp\htdocs\apps
A10: App base URL
A11: http://localhost/apps
A13: API base URL (everything the Network tab shows)
A14: http://localhost/apps/api
A16: Services (XAMPP Control Panel — both must be started)
A17: Apache and MySQL. Nothing else is required: there is no build step, no node process and no queue worker. A hard refresh is enough to pick up changed files — asset URLs are stamped with each file’s modification time by index.php.
A19: Database
... A120: Fill in the Build / environment block on the Summary sheet before you start: date and time of the working tree, the app URL used, the database name, the browser and version for each profile, and the names of the accounts you created. A failure reported without them cannot be reproduced by anyone else.

Sheet Summary
A1: Run summary - multi-user sync follow-up
A2: Counts update automatically from the Pass / Fail column on the Test Cases sheet. Build the environment from the "Test Environment" sheet before you start.
A4: Group | B4: Cases | C4: Pass | D4: Fail | E4: Blocked | F4: Not run | G4: Notes
A5: A. Executive Readiness - saving | B5: =COUNTIF('Test Cases'!$B$2:$B$59,$A5) | C5: =COUNTIFS('Test Cases'!$B$2:$B$59,$A5,'Test Cases'!$L$2:$L$59,"Pass") | D5: =COUNTIFS('Test Cases'!$B$2:$B$59,$A5,'Test Cases'!$L$2:$L$59,"Fail") | E5: =COUNTIFS('Test Cases'!$B$2:$B$59,$A5,'Test Cases'!$L$2:$L$59,"Blocked") | F5: =B5-C5-D5-E5
A6: B. AI Pipeline - saving | B6: =COUNTIF('Test Cases'!$B$2:$B$59,$A6) | C6: =COUNTIFS('Test Cases'!$B$2:$B$59,$A6,'Test Cases'!$L$2:$L$59,"Pass") | D6: =COUNTIFS('Test Cases'!$B$2:$B$59,$A6,'Test Cases'!$L$2:$L$59,"Fail") | E6: =COUNTIFS('Test Cases'!$B$2:$B$59,$A6,'Test Cases'!$L$2:$L$59,"Blocked") | F6: =B6-C6-D6-E6
A7: C. Consistency across modules | B7: =COUNTIF('Test Cases'!$B$2:$B$59,$A7) | C7: =COUNTIFS('Test Cases'!$B$2:$B$59,$A7,'Test Cases'!$L$2:$L$59,"Pass") | D7: =COUNTIFS('Test Cases'!$B$2:$B$59,$A7,'Test Cases'!$L$2:$L$59,"Fail") | E7: =COUNTIFS('Test Cases'!$B$2:$B$59,$A7,'Test Cases'!$L$2:$L$59,"Blocked") | F7: =B7-C7-D7-E7
A8: D. Section-scoped upload | B8: =COUNTIF('Test Cases'!$B$2:$B$59,$A8) | C8: =COUNTIFS('Test Cases'!$B$2:$B$59,$A8,'Test Cases'!$L$2:$L$59,"Pass") | D8: =COUNTIFS('Test Cases'!$B$2:$B$59,$A8,'Test Cases'!$L$2:$L$59,"Fail") | E8: =COUNTIFS('Test Cases'!$B$2:$B$59,$A8,'Test Cases'!$L$2:$L$59,"Blocked") | F8: =B8-C8-D8-E8
A9: E. Section locks | B9: =COUNTIF('Test Cases'!$B$2:$B$59,$A9) | C9: =COUNTIFS('Test Cases'!$B$2:$B$59,$A9,'Test Cases'!$L$2:$L$59,"Pass") | D9: =COUNTIFS('Test Cases'!$B$2:$B$59,$A9,'Test Cases'!$L$2:$L$59,"Fail") | E9: =COUNTIFS('Test Cases'!$B$2:$B$59,$A9,'Test Cases'!$L$2:$L$59,"Blocked") | F9: =B9-C9-D9-E9
A10: F. Reported data loss (must pass) | B10: =COUNTIF('Test Cases'!$B$2:$B$59,$A10) | C10: =COUNTIFS('Test Cases'!$B$2:$B$59,$A10,'Test Cases'!$L$2:$L$59,"Pass") | D10: =COUNTIFS('Test Cases'!$B$2:$B$59,$A10,'Test Cases'!$L$2:$L$59,"Fail") | E10: =COUNTIFS('Test Cases'!$B$2:$B$59,$A10,'Test Cases'!$L$2:$L$59,"Blocked") | F10: =B10-C10-D10-E10
A11: G. Admin - new user form | B11: =COUNTIF('Test Cases'!$B$2:$B$59,$A11) | C11: =COUNTIFS('Test Cases'!$B$2:$B$59,$A11,'Test Cases'!$L$2:$L$59,"Pass") | D11: =COUNTIFS('Test Cases'!$B$2:$B$59,$A11,'Test Cases'!$L$2:$L$59,"Fail") | E11: =COUNTIFS('Test Cases'!$B$2:$B$59,$A11,'Test Cases'!$L$2:$L$59,"Blocked") | F11: =B11-C11-D11-E11
A12: H. Sign-in and identity | B12: =COUNTIF('Test Cases'!$B$2:$B$59,$A12) | C12: =COUNTIFS('Test Cases'!$B$2:$B$59,$A12,'Test Cases'!$L$2:$L$59,"Pass") | D12: =COUNTIFS('Test Cases'!$B$2:$B$59,$A12,'Test Cases'!$L$2:$L$59,"Fail") | E12: =COUNTIFS('Test Cases'!$B$2:$B$59,$A12,'Test Cases'!$L$2:$L$59,"Blocked") | F12: =B12-C12-D12-E12
A13: Total | B13: =SUM(B5:B12) | C13: =SUM(C5:C12) | D13: =SUM(D5:D12) | E13: =SUM(E5:E12) | F13: =SUM(F5:F12)
A15: Build / environment
A16: Build / working tree date + time
A17: App URL
A18: Database
A19: Browser + version (per profile)
A20: Accounts used
A21: Tester(s)
A22: Test run started
A23: Test run finished
A25: Reporting a failure
A26: Give the test case ID, the module, the section and field, the exact value each member entered, the order and rough timing of what each of them did, and screenshots of BOTH windows. For anything about saving, include the Network tab filtered to "workspace" so the uploads can be counted. Say whether the lost value came back after a reload or was gone for good - those are two different faults.

Sheet How to test
A1: How to run this suite
A3: Actual Result and Pass / Fail are left blank on purpose - they are yours to complete. Pass / Fail is a drop-down: Pass, Fail, Blocked, Not Run. The "Reported issue" column names which finding from the 12 August follow-up the case is proving, so a failure can be reported straight back against it. Two columns tell you where to work. "Where to run it (exact screen)" gives the program, the tab, the screen, the exact control and the URL - a field id in [square brackets] is the real element id, so Ctrl+F in dev tools will find it when a label is ambiguous. "Where to verify the result" lists every place the outcome has to be checked: the other member's screen, both reloads, the database, and what the Network tab should show. A case only passes when all of them agree. Build the environment from the "Test Environment" sheet first - accounts, browser profiles, dev tools, the SQL, and three facts that change how the lock cases and ER-10 are run.
A5: Two-user set-up (needed for nearly every case here)
A7: 1. Use two SEPARATE browser profiles, or one normal window and one private/incognito window. Two tabs in the same profile share one sign-in and will not reproduce any of this. 2. Sign in as two different members of the SAME organization, in the SAME program. 3. Put the two windows side by side so both are visible at once. 4. Agree beforehand who types what, and write it down - most of these cases are decided by comparing what was entered against what survived.
A9: Counting uploads
A11: Several cases ask how many times the app uploaded. Open dev tools (F12) > Network, type "workspace" in the filter box, and clear the list before starting. - POST /workspace or POST /workspace/patch = an upload of the user's work. These are what you count. - GET /workspace/rev = the small every-5-seconds check for someone else's changes. Ignore these; they are expected and cost nothing. Click an upload and open its Request payload to see WHAT was sent - the section-scope cases (SC) depend on reading it. Give it long enough. Saves are deliberately grouped: about 0.6 seconds after a click, and up to 1.5 seconds after the last keystroke so that typing does not upload per letter - never more than 4 seconds either way. So wait at least 5 seconds before calling something "not saved". Checking too early is the most common way to report a fault that is not there.
A13: The two "Add" patterns are not the same
A15: The programs build lists differently, and a case written for one reads as a failure in the other: - AI Pipeline: press "Add" and an empty row appears, then type into it. - Executive Readiness: fill the little form in FIRST, then press "+ Add" and the finished row joins the list. Pressing Add on an empty form deliberately adds nothing, and where something must be chosen first the app says so. So in Executive Readiness there is no empty row to type into after pressing Add. ER-03 and ER-13 are written to that program's pattern; PL-03 is written to the Pipeline's. Both must still end in the same place: the row and its text reach the database without anybody navigating away.
A17: Test data
A19: Ann - organization admin / owner. Creates the organization, adds members, edits organization details. Ben - ordinary team member. The second editor in every multi-user case. Cara - ordinary team member. The third editor in DL-04 and LK-05. Super Admin - the app-wide admin passcode, for the admin console cases (AD-*) and SI-07. Use content you can recognise on sight: "ANN-1", "BEN-2" and so on. Every one of these cases is decided by whether a specific value is still there.
A21: ID prefixes
A23: ER Executive Readiness - what saves and when (13 cases) PL AI Pipeline - what saves and when (8 cases) CM The two modules behaving the same way (4 cases) SC Sending only the section that changed (6 cases) LK Section locks - two people, one section (6 cases) DL The reported data loss, end to end (5 cases) AD The admin panel's new-user form (7 cases) SI Sign-in, organization scoping and identity (9 cases) Rows marked "Defect" are the ones that reproduce something in the report. Treat any failure among them as a blocker.
... A37: Admin panel: pressing Save on a new user with a field still missing erased everything already entered, so the whole form had to be retyped to fix one mistake. Covered by AD-01 to AD-07. Sign-in: testers were repeatedly signed in as the organization's administrator without entering those credentials. Clearing cookies, or creating the user from inside the organization page instead of the admin panel, appeared to fix it temporarily - which is the signature of an identity being guessed rather than established. Sign-in must also take an organization, so that the same username in two organizations cannot collide. Covered by SI-01 to SI-09.
